{
  "results": [
    {
      "command": "3.0.5",
      "mean": 7.797133259560002,
      "stddev": 0.10616605169849097,
      "median": 7.7859018548600005,
      "user": 16.193866699999994,
      "system": 1.37619086,
      "min": 7.66661603086,
      "max": 8.04737006486,
      "times": [
        7.832429723860001,
        8.04737006486,
        7.812790386860001,
        7.66661603086,
        7.76546562586,
        7.74518116386,
        7.680649577860001,
        7.77952228186,
        7.84902631186,
        7.792281427860001
      ],
      "exit_codes": [
        0,
        0,
        0,
        0,
        0,
        0,
        0,
        0,
        0,
        0
      ],
      "parameters": {
        "VERSION": "3.0.5"
      }
    },
    {
      "command": "3.6.3",
      "mean": 13.23585322946,
      "stddev": 0.1902695347533353,
      "median": 13.219400203860001,
      "user": 25.5839897,
      "system": 4.19632736,
      "min": 12.98405605186,
      "max": 13.613081170860001,
      "times": [
        12.98405605186,
        13.21562840086,
        13.15330139586,
        13.407404875860001,
        13.35600335986,
        13.09893569786,
        13.22317200686,
        13.613081170860001,
        13.01828928486,
        13.28866004986
      ],
      "exit_codes": [
        0,
        0,
        0,
        0,
        0,
        0,
        0,
        0,
        0,
        0
      ],
      "parameters": {
        "VERSION": "3.6.3"
      }
    },
    {
      "command": "3.8.8",
      "mean": 7.408336604460001,
      "stddev": 0.1329512019899854,
      "median": 7.35654191436,
      "user": 20.157377699999998,
      "system": 1.2910056600000002,
      "min": 7.269775767860001,
      "max": 7.60965858286,
      "times": [
        7.496592815860001,
        7.32207773286,
        7.60965858286,
        7.31847436586,
        7.39100609586,
        7.60200380886,
        7.2820217858600005,
        7.269775767860001,
        7.29105302786,
        7.50070206086
      ],
      "exit_codes": [
        0,
        0,
        0,
        0,
        0,
        0,
        0,
        0,
        0,
        0
      ],
      "parameters": {
        "VERSION": "3.8.8"
      }
    },
    {
      "command": "3.9.9",
      "mean": 7.873891039060001,
      "stddev": 0.1266721400355324,
      "median": 7.869356484360001,
      "user": 21.693768499999997,
      "system": 1.3031908600000002,
      "min": 7.73119642486,
      "max": 8.14898894186,
      "times": [
        7.73119642486,
        7.76514788286,
        7.858537693860001,
        7.89327738286,
        7.88321487486,
        7.737381050860001,
        7.88017527486,
        7.840402049860001,
        8.14898894186,
        8.00058881386
      ],
      "exit_codes": [
        0,
        0,
        0,
        0,
        0,
        0,
        0,
        0,
        0,
        0
      ],
      "parameters": {
        "VERSION": "3.9.9"
      }
    },
    {
      "command": "4.0.0-alpha-13",
      "mean": 9.62905589506,
      "stddev": 0.2119462053734598,
      "median": 9.62641481036,
      "user": 37.036904,
      "system": 2.4468879599999998,
      "min": 9.17422415286,
      "max": 9.92727991386,
      "times": [
        9.92727991386,
        9.829181953860001,
        9.74146598386,
        9.457450596860001,
        9.63671432786,
        9.61611529286,
        9.17422415286,
        9.57750541086,
        9.56324685086,
        9.76737446686
      ],
      "exit_codes": [
        0,
        0,
        0,
        0,
        0,
        0,
        0,
        0,
        0,
        0
      ],
      "parameters": {
        "VERSION": "4.0.0-alpha-13"
      }
    },
    {
      "command": "4.0.0-beta-3",
      "mean": 10.27446124326,
      "stddev": 0.13469344562839805,
      "median": 10.238255522860001,
      "user": 37.3764869,
      "system": 2.17123306,
      "min": 10.13523605186,
      "max": 10.554934902860001,
      "times": [
        10.23912345786,
        10.23738758786,
        10.28547762086,
        10.13523605186,
        10.42174294086,
        10.23427306086,
        10.14180614086,
        10.34758758886,
        10.554934902860001,
        10.14704307986
      ],
      "exit_codes": [
        0,
        0,
        0,
        0,
        0,
        0,
        0,
        0,
        0,
        0
      ],
      "parameters": {
        "VERSION": "4.0.0-beta-3"
      }
    },
    {
      "command": "4.0.0-beta-4",
      "mean": 11.365003230460001,
      "stddev": 0.2593221161556164,
      "median": 11.38833501136,
      "user": 42.079958,
      "system": 2.6089278599999997,
      "min": 10.739625526860001,
      "max": 11.628644254860001,
      "times": [
        11.42711619786,
        11.61749462086,
        11.33286309886,
        10.739625526860001,
        11.349553824860001,
        11.29913243486,
        11.628644254860001,
        11.49717444286,
        11.54282034186,
        11.21560756086
      ],
      "exit_codes": [
        0,
        0,
        0,
        0,
        0,
        0,
        0,
        0,
        0,
        0
      ],
      "parameters": {
        "VERSION": "4.0.0-beta-4"
      }
    }
  ]
}
