{
  "results": [
    {
      "command": "3.0.5",
      "mean": 0.9256551244800001,
      "stddev": 0.015152683784402488,
      "median": 0.92930799738,
      "user": 3.01324414,
      "system": 0.0943497,
      "min": 0.90088375538,
      "max": 0.94282726038,
      "times": [
        0.93072293338,
        0.91473970938,
        0.92789306138,
        0.92070402438,
        0.94055206538,
        0.9341615693800001,
        0.90088375538,
        0.9038253443800001,
        0.9402415213800001,
        0.94282726038
      ],
      "exit_codes": [
        0,
        0,
        0,
        0,
        0,
        0,
        0,
        0,
        0,
        0
      ],
      "parameters": {
        "VERSION": "3.0.5"
      }
    },
    {
      "command": "3.1.1",
      "mean": 0.94201606338,
      "stddev": 0.01943364245835452,
      "median": 0.94124604788,
      "user": 3.17944764,
      "system": 0.10843019999999999,
      "min": 0.91749102338,
      "max": 0.9753087433800001,
      "times": [
        0.95218096338,
        0.9430663743800001,
        0.9218030983800001,
        0.9753087433800001,
        0.92299356038,
        0.9628248753800001,
        0.93942572138,
        0.91749102338,
        0.92885799838,
        0.95620827538
      ],
      "exit_codes": [
        0,
        0,
        0,
        0,
        0,
        0,
        0,
        0,
        0,
        0
      ],
      "parameters": {
        "VERSION": "3.1.1"
      }
    },
    {
      "command": "3.2.5",
      "mean": 1.02994278758,
      "stddev": 0.019528072820545812,
      "median": 1.02650524388,
      "user": 3.48760804,
      "system": 0.11046799999999998,
      "min": 1.00320795838,
      "max": 1.05311086038,
      "times": [
        1.05311086038,
        1.02008834838,
        1.00320795838,
        1.04885433238,
        1.0329221393799999,
        1.05154177838,
        1.01772237638,
        1.01288613238,
        1.00942398738,
        1.0496699623799999
      ],
      "exit_codes": [
        0,
        0,
        0,
        0,
        0,
        0,
        0,
        0,
        0,
        0
      ],
      "parameters": {
        "VERSION": "3.2.5"
      }
    },
    {
      "command": "3.3.9",
      "mean": 1.05284771238,
      "stddev": 0.02364957381543011,
      "median": 1.05976576888,
      "user": 3.53806984,
      "system": 0.1104511,
      "min": 0.9946867743800001,
      "max": 1.07440833438,
      "times": [
        1.06065536638,
        1.06123256338,
        1.05838417238,
        1.07319895438,
        1.03331100938,
        1.06580121238,
        0.9946867743800001,
        1.04792256538,
        1.05887617138,
        1.07440833438
      ],
      "exit_codes": [
        0,
        0,
        0,
        0,
        0,
        0,
        0,
        0,
        0,
        0
      ],
      "parameters": {
        "VERSION": "3.3.9"
      }
    },
    {
      "command": "3.5.4",
      "mean": 1.07728842578,
      "stddev": 0.022618907799632347,
      "median": 1.07442054938,
      "user": 3.52040554,
      "system": 0.16260829999999998,
      "min": 1.0416803773799999,
      "max": 1.11816828438,
      "times": [
        1.08589407538,
        1.05884668238,
        1.07554569738,
        1.05880234238,
        1.07152252438,
        1.07329540138,
        1.11816828438,
        1.0416803773799999,
        1.10597496938,
        1.08315390338
      ],
      "exit_codes": [
        0,
        0,
        0,
        0,
        0,
        0,
        0,
        0,
        0,
        0
      ],
      "parameters": {
        "VERSION": "3.5.4"
      }
    },
    {
      "command": "3.6.3",
      "mean": 1.03982107388,
      "stddev": 0.02093835478338468,
      "median": 1.03823190538,
      "user": 3.3686823400000003,
      "system": 0.1698571,
      "min": 1.00727337938,
      "max": 1.06819760538,
      "times": [
        1.04116573038,
        1.06801154938,
        1.05574963638,
        1.01380820138,
        1.02844036738,
        1.03003160838,
        1.05023458038,
        1.00727337938,
        1.06819760538,
        1.03529808038
      ],
      "exit_codes": [
        0,
        0,
        0,
        0,
        0,
        0,
        0,
        0,
        0,
        0
      ],
      "parameters": {
        "VERSION": "3.6.3"
      }
    },
    {
      "command": "3.8.1",
      "mean": 1.04798411788,
      "stddev": 0.020607412021108416,
      "median": 1.04622769138,
      "user": 3.3836244399999997,
      "system": 0.150315,
      "min": 1.0205835563799999,
      "max": 1.08913905838,
      "times": [
        1.0205835563799999,
        1.06772452538,
        1.04430324338,
        1.03755490638,
        1.04315172038,
        1.04949132838,
        1.08913905838,
        1.02105347538,
        1.04815213938,
        1.05868722538
      ],
      "exit_codes": [
        0,
        0,
        0,
        0,
        0,
        0,
        0,
        0,
        0,
        0
      ],
      "parameters": {
        "VERSION": "3.8.1"
      }
    },
    {
      "command": "3.8.2",
      "mean": 1.00977135728,
      "stddev": 0.019818924395948134,
      "median": 1.00905148688,
      "user": 3.28120354,
      "system": 0.08802169999999998,
      "min": 0.97279202438,
      "max": 1.04356735138,
      "times": [
        1.00893704938,
        1.04356735138,
        1.02256302838,
        0.97279202438,
        1.02544430038,
        1.00750426438,
        0.99207955738,
        0.99579965738,
        1.01986041538,
        1.00916592438
      ],
      "exit_codes": [
        0,
        0,
        0,
        0,
        0,
        0,
        0,
        0,
        0,
        0
      ],
      "parameters": {
        "VERSION": "3.8.2"
      }
    },
    {
      "command": "3.8.3",
      "mean": 0.98095326768,
      "stddev": 0.0182220049128797,
      "median": 0.9790262138800001,
      "user": 3.2160426400000004,
      "system": 0.0895663,
      "min": 0.95583445438,
      "max": 1.01523526638,
      "times": [
        0.9682981833800001,
        0.9694897543800001,
        0.9754635903800001,
        1.00371633538,
        0.9647041993800001,
        0.98703534938,
        0.98258883738,
        1.01523526638,
        0.95583445438,
        0.98716670638
      ],
      "exit_codes": [
        0,
        0,
        0,
        0,
        0,
        0,
        0,
        0,
        0,
        0
      ],
      "parameters": {
        "VERSION": "3.8.3"
      }
    },
    {
      "command": "3.8.4",
      "mean": 0.97571860858,
      "stddev": 0.01585451301754653,
      "median": 0.97292173688,
      "user": 3.19852834,
      "system": 0.08786779999999998,
      "min": 0.94811687138,
      "max": 0.9945124683800001,
      "times": [
        0.9900399963800001,
        0.99248922838,
        0.9945124683800001,
        0.98993981938,
        0.97102941738,
        0.97225049838,
        0.95643146038,
        0.97359297538,
        0.94811687138,
        0.9687833503800001
      ],
      "exit_codes": [
        0,
        0,
        0,
        0,
        0,
        0,
        0,
        0,
        0,
        0
      ],
      "parameters": {
        "VERSION": "3.8.4"
      }
    },
    {
      "command": "3.8.5",
      "mean": 0.9887256495799999,
      "stddev": 0.02828680801836426,
      "median": 0.98638614038,
      "user": 3.2244288400000003,
      "system": 0.09344430000000001,
      "min": 0.9416602283800001,
      "max": 1.03507894538,
      "times": [
        0.98665699838,
        1.00035466738,
        1.02282214338,
        0.98611528238,
        1.00761167138,
        0.9416602283800001,
        0.96898618638,
        0.96777866538,
        1.03507894538,
        0.97019170738
      ],
      "exit_codes": [
        0,
        0,
        0,
        0,
        0,
        0,
        0,
        0,
        0,
        0
      ],
      "parameters": {
        "VERSION": "3.8.5"
      }
    },
    {
      "command": "3.8.6",
      "mean": 0.9934435491800002,
      "stddev": 0.024393969263715808,
      "median": 0.98665488338,
      "user": 3.232689739999999,
      "system": 0.08415429999999999,
      "min": 0.9660909963800001,
      "max": 1.05140402038,
      "times": [
        0.98894234338,
        1.05140402038,
        0.98436742338,
        0.9936255003800001,
        0.9660909963800001,
        1.01099690938,
        0.97825934138,
        0.97856586438,
        0.9774121223800001,
        1.00477097038
      ],
      "exit_codes": [
        0,
        0,
        0,
        0,
        0,
        0,
        0,
        0,
        0,
        0
      ],
      "parameters": {
        "VERSION": "3.8.6"
      }
    },
    {
      "command": "3.8.7",
      "mean": 0.9782269296800001,
      "stddev": 0.017205857391686525,
      "median": 0.97066553588,
      "user": 3.17918434,
      "system": 0.084421,
      "min": 0.95661706538,
      "max": 1.00886752038,
      "times": [
        1.00886752038,
        0.9836435813800001,
        0.97172542038,
        1.00328983638,
        0.96892122838,
        0.95661706538,
        0.9694766943800001,
        0.9873340713800001,
        0.96278822738,
        0.96960565138
      ],
      "exit_codes": [
        0,
        0,
        0,
        0,
        0,
        0,
        0,
        0,
        0,
        0
      ],
      "parameters": {
        "VERSION": "3.8.7"
      }
    },
    {
      "command": "3.8.8",
      "mean": 1.0067877760800001,
      "stddev": 0.012348458457894045,
      "median": 1.00847633038,
      "user": 3.29380144,
      "system": 0.0913841,
      "min": 0.98741190038,
      "max": 1.02481315538,
      "times": [
        1.02379144038,
        1.01204699338,
        1.00893831938,
        0.99577935738,
        1.01296626138,
        0.98741190038,
        1.02481315538,
        0.99751159538,
        0.99660439638,
        1.00801434138
      ],
      "exit_codes": [
        0,
        0,
        0,
        0,
        0,
        0,
        0,
        0,
        0,
        0
      ],
      "parameters": {
        "VERSION": "3.8.8"
      }
    },
    {
      "command": "3.9.0",
      "mean": 1.2359247221799998,
      "stddev": 0.032187581394516655,
      "median": 1.23783949788,
      "user": 4.00167024,
      "system": 0.09385189999999999,
      "min": 1.19332780638,
      "max": 1.28763064238,
      "times": [
        1.23749342638,
        1.24664905438,
        1.23818556938,
        1.19428657138,
        1.19332780638,
        1.24565303838,
        1.28235223038,
        1.21754636938,
        1.21612251338,
        1.28763064238
      ],
      "exit_codes": [
        0,
        0,
        0,
        0,
        0,
        0,
        0,
        0,
        0,
        0
      ],
      "parameters": {
        "VERSION": "3.9.0"
      }
    },
    {
      "command": "3.9.1",
      "mean": 1.2334386801799997,
      "stddev": 0.020402713939245,
      "median": 1.2331349563799998,
      "user": 4.0453626400000005,
      "system": 0.10374969999999999,
      "min": 1.19629062338,
      "max": 1.26145320638,
      "times": [
        1.25551332938,
        1.2517163813799999,
        1.26145320638,
        1.21788252138,
        1.2207122023799999,
        1.19629062338,
        1.21927958738,
        1.23593685338,
        1.24526903738,
        1.23033305938
      ],
      "exit_codes": [
        0,
        0,
        0,
        0,
        0,
        0,
        0,
        0,
        0,
        0
      ],
      "parameters": {
        "VERSION": "3.9.1"
      }
    },
    {
      "command": "4.0.0-alpha-5",
      "mean": 1.5634528399799998,
      "stddev": 0.020690500319397974,
      "median": 1.56029037638,
      "user": 5.51236124,
      "system": 0.15851099999999999,
      "min": 1.53835260238,
      "max": 1.6137473473800001,
      "times": [
        1.54790703138,
        1.56163301938,
        1.55963694738,
        1.56094380538,
        1.55671747738,
        1.55065166538,
        1.6137473473800001,
        1.53835260238,
        1.5671945443800002,
        1.57774395938
      ],
      "exit_codes": [
        0,
        0,
        0,
        0,
        0,
        0,
        0,
        0,
        0,
        0
      ],
      "parameters": {
        "VERSION": "4.0.0-alpha-5"
      }
    }
  ]
}
