{
  "results": [
    {
      "command": "3.0.5",
      "mean": 0.9882001067399999,
      "stddev": 0.024331100784145236,
      "median": 0.97987776134,
      "user": 3.31575418,
      "system": 0.11949446000000001,
      "min": 0.9497775028400001,
      "max": 1.03006307784,
      "times": [
        0.9755267078400001,
        0.9714248448400001,
        0.9962086418400001,
        0.97606300584,
        1.0217597028399998,
        0.9816324148400001,
        0.9781231078400001,
        1.03006307784,
        0.9497775028400001,
        1.00142206084
      ],
      "exit_codes": [
        0,
        0,
        0,
        0,
        0,
        0,
        0,
        0,
        0,
        0
      ],
      "parameters": {
        "VERSION": "3.0.5"
      }
    },
    {
      "command": "3.6.3",
      "mean": 1.1057693079399997,
      "stddev": 0.01739316225395528,
      "median": 1.1015970623399998,
      "user": 3.72986398,
      "system": 0.18469945999999995,
      "min": 1.08284369784,
      "max": 1.1329139908399999,
      "times": [
        1.0963423798399998,
        1.12667475784,
        1.1329139908399999,
        1.11574893484,
        1.09618249384,
        1.0931487148399999,
        1.10685174484,
        1.0865806998399998,
        1.1204056648399998,
        1.08284369784
      ],
      "exit_codes": [
        0,
        0,
        0,
        0,
        0,
        0,
        0,
        0,
        0,
        0
      ],
      "parameters": {
        "VERSION": "3.6.3"
      }
    },
    {
      "command": "3.8.8",
      "mean": 1.0511882834399997,
      "stddev": 0.028090528816100788,
      "median": 1.0545880913399999,
      "user": 3.5488238799999996,
      "system": 0.10244685999999999,
      "min": 1.01242530184,
      "max": 1.08916404984,
      "times": [
        1.06825435084,
        1.0195126158399999,
        1.01242530184,
        1.08661601984,
        1.02483575984,
        1.0719422238399998,
        1.05660735384,
        1.0299563298399999,
        1.05256882884,
        1.08916404984
      ],
      "exit_codes": [
        0,
        0,
        0,
        0,
        0,
        0,
        0,
        0,
        0,
        0
      ],
      "parameters": {
        "VERSION": "3.8.8"
      }
    },
    {
      "command": "3.9.4",
      "mean": 1.2042691740399998,
      "stddev": 0.018781015665967137,
      "median": 1.20683182584,
      "user": 4.03361658,
      "system": 0.10772736000000001,
      "min": 1.17966433384,
      "max": 1.2313923088399998,
      "times": [
        1.1861977208399999,
        1.21228004784,
        1.2243623638399999,
        1.19269802784,
        1.2313923088399998,
        1.2087388208399998,
        1.18040734684,
        1.20492483084,
        1.2220259388399999,
        1.17966433384
      ],
      "exit_codes": [
        0,
        0,
        0,
        0,
        0,
        0,
        0,
        0,
        0,
        0
      ],
      "parameters": {
        "VERSION": "3.9.4"
      }
    },
    {
      "command": "3.9.5",
      "mean": 1.21356637654,
      "stddev": 0.027586857421472433,
      "median": 1.2083763248400001,
      "user": 4.03108538,
      "system": 0.10590485999999999,
      "min": 1.17501404284,
      "max": 1.26933929784,
      "times": [
        1.21554792084,
        1.23184647784,
        1.1889834048399999,
        1.19912534784,
        1.2406562108399999,
        1.20190882184,
        1.19839841284,
        1.26933929784,
        1.17501404284,
        1.21484382784
      ],
      "exit_codes": [
        0,
        0,
        0,
        0,
        0,
        0,
        0,
        0,
        0,
        0
      ],
      "parameters": {
        "VERSION": "3.9.5"
      }
    },
    {
      "command": "4.0.0-alpha-7",
      "mean": 1.5348438867399998,
      "stddev": 0.012477670799828118,
      "median": 1.53590748184,
      "user": 5.14070028,
      "system": 0.15880615999999997,
      "min": 1.5186803118399999,
      "max": 1.5502336698399999,
      "times": [
        1.5186803118399999,
        1.52629659284,
        1.52191471584,
        1.53996875184,
        1.5474156158399999,
        1.5502336698399999,
        1.53184621184,
        1.54719030184,
        1.5200835988399999,
        1.54480909684
      ],
      "exit_codes": [
        0,
        0,
        0,
        0,
        0,
        0,
        0,
        0,
        0,
        0
      ],
      "parameters": {
        "VERSION": "4.0.0-alpha-7"
      }
    },
    {
      "command": "4.0.0-alpha-8",
      "mean": 1.66147863464,
      "stddev": 0.044607200343246736,
      "median": 1.65468249234,
      "user": 5.4309281799999995,
      "system": 0.16689246,
      "min": 1.59664266084,
      "max": 1.72120511484,
      "times": [
        1.65768712684,
        1.63034701784,
        1.61068125084,
        1.69707115184,
        1.63298928684,
        1.7046994628399998,
        1.71178541584,
        1.72120511484,
        1.65167785784,
        1.59664266084
      ],
      "exit_codes": [
        0,
        0,
        0,
        0,
        0,
        0,
        0,
        0,
        0,
        0
      ],
      "parameters": {
        "VERSION": "4.0.0-alpha-8"
      }
    }
  ]
}
